README.md
setup.py
m_olap_sdk.egg-info/PKG-INFO
m_olap_sdk.egg-info/SOURCES.txt
m_olap_sdk.egg-info/dependency_links.txt
m_olap_sdk.egg-info/entry_points.txt
m_olap_sdk.egg-info/namespace_packages.txt
m_olap_sdk.egg-info/requires.txt
m_olap_sdk.egg-info/top_level.txt
mobio/libs/__init__.py
mobio/libs/olap/__init__.py
mobio/libs/olap/mining_warehouse/__init__.py
mobio/libs/olap/mining_warehouse/datatype.py
mobio/libs/olap/mining_warehouse/dialect.py
mobio/libs/olap/mining_warehouse/reflection.py
mobio/libs/olap/mining_warehouse/requirements.py
mobio/libs/olap/mining_warehouse/base_engine/__init__.py
mobio/libs/olap/mining_warehouse/base_engine/base_session.py
mobio/libs/olap/mining_warehouse/base_engine/engines.py